feito
feito/github
