Metadata-Version: 1.1
Name: feito
Version: 0.0.5
Summary: Automated code review in Python
Home-page: http://github.com/magrathealabs/feito
Author: Magrathea Labs
Author-email: contact@magrathealabs.com
License: MIT
Keywords: code review,good code,linter,coverage,pronto for python
Platform: UNKNOWN
Classifier: Development Status :: 3 - Alpha
Classifier: Intended Audience :: Developers
Classifier: Intended Audience :: Information Technology
Classifier: License :: OSI Approved :: MIT License
Classifier: Operating System :: OS Independent
Classifier: Programming Language :: Python :: 3 :: Only
Classifier: Topic :: Software Development :: Libraries :: Python Modules
Classifier: Topic :: Software Development :: Quality Assurance
Classifier: Topic :: Software Development :: Testing
Classifier: Topic :: Utilities
